{"id":310993,"sku":"6705260033853","name":"Chu\u1ed9t Kh\u00f4ng D\u00e2y Genius NX7005 - H\u00e0ng ch\u00ednh h\u00e3ng","url_key":"chuot-khong-day-genius-nx7005-hang-chinh-hang-p310993","url_path":"chuot-khong-day-genius-nx7005-hang-chinh-hang-p310993.html?spid=310995","type":"configurable","book_cover":null,"short_description":"Thi\u1ebft k\u1ebf c\u00e2n \u0111\u1ed1i, v\u1eeba tay\nChu\u1ed9t Kh\u00f4ng D\u00e2y Genius NX7005 \u0111\u01b0\u1ee3c gia c\u00f4ng t\u1eeb ch\u1ea5t li\u1ec7u nh\u1ef1a nh\u00e1m \u1edf th\u00e2n chu\u1ed9t v\u00e0 nh\u1ef1a b\u00f3ng \u1edf 2 b\u00ean tay c\u1ea7m tr\u00f4ng r\u1ea5t sang v\u00e0 \u0111\u1eb9p m\u1eaft. Thi\u1ebft k\u1ebf c\u00e2n x\u1ee9ng c\u00f3 th\u1ec3 s\u1eed d\u1ee5ng \u0111\u01b0\u1ee3c...","price":117000,"list_price":180000,"price_usd":5.0010000000000003,"badges":[{"code":"tikinow","text":"tikinow"},{"code":"is_genuine"}],"discount":63000,"discount_rate":35,"rating_average":4,"review_count":292,"order_count":0,"favourite_count":0,"thumbnail_url":"https:\/\/salt.tikicdn.com\/cache\/280x280\/media\/catalog\/product\/n\/x\/nx7005den--1-.u2470.d20170214.t135317.735769.jpg","has_ebook":false,"inventory_status":"available","is_visible":true,"productset_group_name":"Thi\u1ebft B\u1ecb S\u1ed1 - Ph\u1ee5 Ki\u1ec7n S\u1ed1\/Ph\u1ee5 ki\u1ec7n m\u00e1y t\u00ednh v\u00e0 Laptop\/Ph\u1ee5 Ki\u1ec7n Ph\u00edm Chu\u1ed9t V\u0103n Ph\u00f2ng\/Chu\u1ed9t V\u0103n Ph\u00f2ng\/Chu\u1ed9t V\u0103n Ph\u00f2ng Kh\u00f4ng D\u00e2y","is_fresh":false,"seller":null,"is_flower":false,"is_gift_card":false,"inventory":{"product_virtual_type":null,"fulfillment_type":"tiki_delivery"},"url_attendant_input_form":"","master_id":null,"salable_type":"","data_version":10,"day_ago_created":1442,"categories":{"id":1838,"name":"Chu\u1ed9t V\u0103n Ph\u00f2ng Kh\u00f4ng D\u00e2y","is_leaf":true},"meta_title":"Chu\u1ed9t Kh\u00f4ng D\u00e2y Genius NX7005 ch\u00ednh h\u00e3ng","meta_description":null,"meta_keywords":null,"liked":false,"rating_summary":[],"description":"<span class='description-separate'><\/span>S\u1eed d\u1ee5ng c\u00f4ng ngh\u1ec7 1200 dpi BlueEye gi\u00fap s\u1eed d\u1ee5ng t\u1ed1t tr\u00ean m\u1ecdi b\u1ec1 m\u1eb7t<br \/>\nThi\u1ebft k\u1ebf c\u00e2n \u0111\u1ed1i s\u1eed d\u1ee5ng \u0111\u01b0\u1ee3c c\u1ea3 cho ng\u01b0\u1eddi thu\u1eadn tay tr\u00e1i v\u00e0 ph\u1ea3i<br \/>\n\u1ee8ng d\u1ee5ng SmartGenius h\u1ed7 tr\u1ee3 tu\u1ef3 ch\u1ec9nh thi\u1ebft b\u1ecb \u0111\u1ec3 c\u00f3 hi\u1ec7u su\u1ea5t t\u1ed1i \u01b0u<br \/>\nThi\u1ebft k\u1ebf tr\u1ebb trung v\u00e0 n\u0103ng \u0111\u1ed9ng, ti\u1ec7n l\u1ee3i<br \/>\n<br \/><h5>Thi\u1ebft k\u1ebf c\u00e2n \u0111\u1ed1i, v\u1eeba tay<\/h5>\n<p><strong>Chu\u1ed9t Kh\u00f4ng D\u00e2y Genius NX7005<\/strong> \u0111\u01b0\u1ee3c gia c\u00f4ng t\u1eeb ch\u1ea5t li\u1ec7u nh\u1ef1a nh\u00e1m \u1edf th\u00e2n chu\u1ed9t v\u00e0 nh\u1ef1a b\u00f3ng \u1edf 2 b\u00ean tay c\u1ea7m tr\u00f4ng r\u1ea5t sang v\u00e0 \u0111\u1eb9p m\u1eaft. Thi\u1ebft k\u1ebf c\u00e2n x\u1ee9ng c\u00f3 th\u1ec3 s\u1eed d\u1ee5ng \u0111\u01b0\u1ee3c c\u1ea3 cho ng\u01b0\u1eddi thu\u1eadn tay tr\u00e1i v\u00e0 tay ph\u1ea3i. S\u1ea3n ph\u1ea9m c\u00f3 k\u00edch th\u01b0\u1edbc nh\u1ecf g\u1ecdn v\u00e0 r\u1ea5t nh\u1eb9 ch\u1ec9 80g \u0111\u1ea9y nhanh t\u1ed1c \u0111\u1ed9 l\u01b0\u1edbt v\u00e0 r\u1ea5t thu\u1eadn ti\u1ec7n khi mang b\u00ean m\u00ecnh. B\u1ea1n c\u00f3 th\u1ec3 c\u1ea7m tr\u00ean tay con chu\u1ed9t n\u00e0y c\u1ea3 ng\u00e0y m\u00e0 kh\u00f4ng h\u1ec1 c\u1ea3m th\u1ea5y m\u1ecfi t\u00ed n\u00e0o.<\/p>\n<p><img src=\"https:\/\/salt.tikicdn.com\/ts\/tmp\/92\/c9\/36\/63158af21593dcf367cc1b2529801c9c.jpg\" alt=\"Chu\u1ed9t Kh\u00f4ng D\u00e2y Genius NX7005\" width=\"750\" height=\"500\" \/><\/p>\n<h5>C\u00f4ng ngh\u1ec7 c\u1ea3m bi\u1ebfn quang h\u1ecdc ti\u00ean ti\u1ebfn<\/h5>\n<p>NX7005 trang b\u1ecb c\u00f4ng ngh\u1ec7 c\u1ea3m bi\u1ebfn quang h\u1ecdc ti\u00ean ti\u1ebfn c\u00f3 \u0111\u1ed9 ph\u00e2n gi\u1ea3i cao l\u00ean t\u1edbi 1200dpi cho ph\u00e9p b\u1ea1n di chuy\u1ec3n con tr\u1ecf tr\u00ean m\u00e0n h\u00ecnh v\u1edbi t\u1ed1c \u0111\u1ed9 nhanh, m\u01b0\u1ee3t v\u00e0 ch\u00ednh x\u00e1c \u0111\u1ea3m b\u1ea3o \u0111em l\u1ea1i nh\u1eefng tr\u1ea3i nghi\u1ec7m l\u00e0m vi\u1ec7c, ch\u01a1i game th\u00fa v\u1ecb. Ngo\u00e0i ra n\u1ebfu kh\u00f4ng quen v\u1edbi t\u1ed1c \u0111\u1ed9 nhanh n\u00e0y, b\u1ea1n c\u00f3 th\u1ec3 h\u1ea1 dpi th\u1ea5p xu\u1ed1ng. M\u1eb7c d\u00f9 kh\u00f4ng ph\u1ea3i l\u00e0 s\u1ea3n ph\u1ea9m gaming nh\u01b0ng NX7005 c\u00f3 th\u1ec3 \u0111\u00e1p \u1ee9ng t\u1ed1t nhu c\u1ea7u c\u1ee7a c\u00e1c game th\u1ee7 th\u01b0\u1eddng s\u1eed d\u1ee5ng DPI cao 1200.<\/p>\n<p><img src=\"https:\/\/salt.tikicdn.com\/ts\/tmp\/8b\/30\/33\/35e3dcb5e3ad1705ed7d9594f70b291b.jpg\" alt=\"Chu\u1ed9t Kh\u00f4ng D\u00e2y Genius NX7005\" width=\"750\" height=\"500\" \/><\/p>\n<h5>M\u1eaft \u0111\u1ecdc BlueEye l\u01b0\u1edbt tr\u00ean m\u1ecdi b\u1ec1 m\u1eb7t<\/h5>\n<p>\u0110\u1eb1ng sau chu\u1ed9t l\u00e0 m\u1ed9t m\u1eaft \u0111\u1ecdc BlueEye c\u00f3 kh\u1ea3 n\u0103ng t\u00e1i t\u1ea1o t\u1ed1t h\u00ecnh \u1ea3nh b\u00e0n di. BlueEye gi\u00fap ng\u01b0\u1eddi d\u00f9ng c\u00f3 th\u1ec3 thao t\u00e1c con tr\u1ecf ch\u00ednh x\u00e1c, l\u01b0\u1edbt m\u01b0\u1ee3t tr\u00ean nhi\u1ec1u b\u1ec1 m\u1eb7t nh\u01b0 g\u1ed7, k\u00ednh trong su\u1ed1t, gh\u1ebf sofa ho\u1eb7c th\u1eadm ch\u00ed l\u00e0 tr\u00ean t\u1ea5m th\u1ea3m.<\/p>\n<p><img src=\"https:\/\/salt.tikicdn.com\/ts\/tmp\/8d\/fc\/34\/f4cd93a7d376466cca26c56f3680a53e.jpg\" alt=\"Chu\u1ed9t Kh\u00f4ng D\u00e2y Genius NX7005\" width=\"750\" height=\"500\" \/><\/p>\n<h5>S\u1eed d\u1ee5ng s\u00f3ng Wireless 2.4GHz kho\u1ea3ng c\u00e1ch xa v\u00e0 nh\u1ea1y<\/h5>\n<p>Genius NX7005 \u0111\u01b0\u1ee3c \u00e1p d\u1ee5ng m\u1ee9c \u0111\u1ed9 s\u00f3ng Wireless l\u00e0 2.4GHz cho ph\u00e9p b\u1ea1n s\u1eed d\u1ee5ng chu\u1ed9t trong kho\u1ea3ng c\u00e1ch t\u1ed1i \u0111a 10m v\u00e0 t\u0103ng t\u1ed1c \u0111\u1ed9 truy\u1ec1n d\u1eef li\u1ec7u \u0111\u1ebfn m\u00e1y t\u00ednh. B\u1ea1n ch\u1ec9 c\u1ea7n c\u1eafm \u0111\u1ea7u USB c\u1ee7a chu\u1ed9t v\u00e0o m\u00e1y l\u00e0 \u0111\u00e3 c\u00f3 th\u1ec3 s\u1eed d\u1ee5ng ngay l\u1eadp t\u1ee9c.<\/p>\n<p><img src=\"https:\/\/salt.tikicdn.com\/ts\/tmp\/83\/57\/e7\/db0aecd9be9c83a439f3e700a0f39741.jpg\" alt=\"Chu\u1ed9t Kh\u00f4ng D\u00e2y Genius NX7005\" width=\"750\" height=\"500\" \/><\/p>\n<h5>\u0110\u1ea7u n\u1ed1i USB \u0111a n\u0103ng<\/h5>\n<p>Ngo\u00e0i ra \u0111\u1ea7u USB k\u1ebft n\u1ed1i c\u1ee7a chu\u1ed9t c\u00f3 th\u1ec3 s\u1eed d\u1ee5ng v\u1edbi c\u00e1c chu\u1ed9t kh\u00f4ng d\u00e2y Genius kh\u00e1c. V\u00ec v\u1eady n\u1ebfu b\u1ea1n c\u00f3 s\u1edf h\u1eefu nh\u1eefng con chu\u1ed9t Genius\u00a0\u0111\u1ec3 s\u1eed d\u1ee5ng cho nhi\u1ec1u m\u1ee5c \u0111\u00edch kh\u00e1c nhau s\u1ebd \u0111\u1ed3ng th\u1eddi gi\u00fap \u0111\u1ee1 b\u1ea1n r\u1ea5t nhi\u1ec1u n\u1ebfu c\u00f3 l\u1ee1 \u0111\u00e1nh r\u01a1i \u0111\u1ea7u c\u1eafm USB - m\u1ed9t th\u1ee9 nh\u1ecf b\u00e9 r\u1ea5t d\u1ec5 \u201c\u0111i l\u1ea1c\u201d trong th\u1eddi gian l\u00e0m vi\u1ec7c.<\/p>\n<p><img src=\"https:\/\/salt.tikicdn.com\/ts\/tmp\/3f\/0f\/77\/7305e14920bb60c4237c4e82effda64b.jpg\" alt=\"Chu\u1ed9t Kh\u00f4ng D\u00e2y Genius NX7005\" width=\"750\" height=\"500\" \/><\/p>\n<h5>C\u00e1c ph\u00edm b\u1ed1 tr\u00ed h\u1ee3p l\u00ed, thu\u1eadn ti\u1ec7n<\/h5>\n<p>Chu\u1ed9t m\u00e1y t\u00ednh GENIUS NX7005 c\u00f3 3 n\u00fat c\u01a1 b\u1ea3n g\u1ed3m 1 bi l\u0103n ch\u00ednh gi\u1eefa v\u00e0 2 chu\u1ed9t tr\u00e1i ph\u1ea3i. Con l\u0103n \u0111\u01b0\u1ee3c thi\u1ebft k\u1ebf b\u00e1nh r\u0103ng nh\u1eb1m h\u1ea1n ch\u1ebf b\u1ecb tr\u01a1n tr\u01b0\u1ee3t khi cu\u1ed9n v\u00e0 \u0111\u1eb7c bi\u1ec7t kh\u00f4ng g\u00e2y ti\u1ebfng \u0111\u1ed9ng \u1ed3n \u00e0o. Hai n\u00fat tr\u00e1i\/ph\u1ea3i chu\u1ed9t b\u1ea5m r\u1ea5t \u00eam v\u00e0 nh\u1ea1y.<\/p>\n<p><img src=\"https:\/\/salt.tikicdn.com\/ts\/tmp\/d9\/74\/45\/6cc580d02a70344568dacd9fa46bcb02.jpg\" alt=\"Chu\u1ed9t Kh\u00f4ng D\u00e2y Genius NX7005\" width=\"750\" height=\"500\" \/><\/p>\n<h5>Pin AA d\u1ec5 s\u1eed d\u1ee5ng, thay th\u1ebf<\/h5>\n<p>\u0110\u1eb1ng sau chu\u1ed9t g\u1ed3m n\u1eafp m\u1edf thay pin AA v\u00e0 m\u1ed9t c\u00f4ng t\u1eafc b\u1eadt\/t\u1eaft chu\u1ed9t. C\u00f4ng t\u1eafc \u0111\u01b0\u1ee3c b\u1ed5 sung gi\u00fap ti\u1ebft ki\u1ec7m pin hi\u1ec7u qu\u1ea3 m\u1ed7i khi b\u1ea1n kh\u00f4ng s\u1eed d\u1ee5ng chu\u1ed9t.<\/p>\n<p><img src=\"https:\/\/salt.tikicdn.com\/ts\/tmp\/0f\/83\/24\/853f7794e441e87f2aad44a42beb978b.jpg\" alt=\"Chu\u1ed9t Kh\u00f4ng D\u00e2y Genius NX7005\" width=\"750\" height=\"500\" \/><\/p><p>Gi\u00e1 s\u1ea3n ph\u1ea9m tr\u00ean Tiki \u0111\u00e3 bao g\u1ed3m thu\u1ebf theo lu\u1eadt hi\u1ec7n h\u00e0nh. Tuy nhi\u00ean tu\u1ef3 v\u00e0o t\u1eebng lo\u1ea1i s\u1ea3n ph\u1ea9m ho\u1eb7c ph\u01b0\u01a1ng th\u1ee9c, \u0111\u1ecba ch\u1ec9 giao h\u00e0ng m\u00e0 c\u00f3 th\u1ec3 ph\u00e1t sinh th\u00eam chi ph\u00ed kh\u00e1c nh\u01b0 ph\u00ed v\u1eadn chuy\u1ec3n, ph\u1ee5 ph\u00ed h\u00e0ng c\u1ed3ng k\u1ec1nh, ...<\/p>","return_policy":null,"warranty_policy":null,"brand":{"id":19071,"name":"Genius","slug":"genius"},"seller_specifications":[{"name":"Tiki ho\u00e0n ti\u1ec1n 111% n\u1ebfu ph\u00e1t hi\u1ec7n h\u00e0ng gi\u1ea3","value":null,"url":null},{"name":"Cam k\u1ebft h\u00e0ng ch\u00ednh hi\u1ec7u","value":null,"url":null},{"name":"Th\u1eddi gian b\u1ea3o h\u00e0nh: 12 th\u00e1ng ch\u00ednh h\u00e3ng","value":null,"url":"http:\/\/tiki.vn\/doi-tra-de-dang"}],"current_seller":{"id":1,"sku":"6703863490462","store_id":40395,"name":"Tiki Trading","slug":"tiki-trading","link":"https:\/\/tiki.vn\/cua-hang\/tiki-trading","is_best_store":false,"logo":"https:\/\/vcdn.tikicdn.com\/ts\/seller\/ee\/fa\/a0\/98f3f134f85cff2c6972c31777629aa0.png","product_id":"310995","price":117000,"is_offline_installment_supported":null},"other_sellers":[{"id":915,"name":"Nova Computer","link":"https:\/\/tiki.vn\/cua-hang\/nova-computer","logo":"https:\/\/vcdn.tikicdn.com\/ts\/seller\/bc\/00\/16\/1975464e46924a9f4a143bbf9b0c5b93.jpg","product_id":"952078","price":139000,"store_id":874},{"id":9980,"name":"Minh Chau Computer","link":"https:\/\/tiki.vn\/cua-hang\/minh-chau-computer","logo":"https:\/\/vcdn.tikicdn.com\/ts\/seller\/2f\/57\/c9\/221b89250299d3287999ea922b3c5dc9.jpg","product_id":"8380906","price":128900,"store_id":9770},{"id":53535,"name":"Clickshop2019","link":"https:\/\/tiki.vn\/cua-hang\/clickshop2019","logo":"https:\/\/vcdn.tikicdn.com\/ts\/seller\/e9\/9d\/f1\/3954232a10e08a8ce5ec6feed7ea0587.jpg","product_id":"20211457","price":140000,"store_id":50895},{"id":417,"name":"Vi T\u00ednh Qu\u1ed1c Vy","link":"https:\/\/tiki.vn\/cua-hang\/vi-tinh-quoc-vy","logo":"https:\/\/vcdn.tikicdn.com\/ts\/seller\/bf\/2e\/04\/bf2e0434dbfe1a0c41ac490a7a33c015.jpg","product_id":"49640747","price":150000,"store_id":380},{"id":20367,"name":"VI T\u00cdNH NAM TRUNG H\u1ea2I","link":"https:\/\/tiki.vn\/cua-hang\/vi-tinh-nam-trung-hai","logo":"https:\/\/vcdn.tikicdn.com\/ts\/seller\/e0\/4a\/74\/e7144f9e9f87ee90acb39c1068e9b422.png","product_id":"54777219","price":124500,"store_id":19857},{"id":2786,"name":"Ng\u1ecdc Ti\u1ebfn Mobile","link":"https:\/\/tiki.vn\/cua-hang\/ngoc-tien-mobile","logo":"https:\/\/vcdn.tikicdn.com\/ts\/seller\/7a\/74\/45\/18fb717e452fce5719610e32644773df.jpg","product_id":"58410596","price":180000,"store_id":2740}],"configurable_options":[{"code":"option1","name":"M\u00e0u","position":0,"values":[{"label":"Black"}]}],"configurable_products":[{"child_id":574766,"sku":"6704134251126","name":"Chu\u1ed9t Kh\u00f4ng D\u00e2y Genius NX7005 - H\u00e0ng ch\u00ednh h\u00e3ng  - Black","price":117000,"thumbnail_url":"https:\/\/salt.tikicdn.com\/cache\/280x280\/media\/catalog\/product\/n\/x\/nx7005den--1-.u2470.d20170214.t135317.735769.jpg","images":[{"large_url":"https:\/\/salt.tikicdn.com\/cache\/w1200\/media\/catalog\/product\/n\/x\/nx7005den--1-.u2470.d20170214.t135317.735769.jpg","medium_url":"https:\/\/salt.tikicdn.com\/cache\/550x550\/media\/catalog\/product\/n\/x\/nx7005den--1-.u2470.d20170214.t135317.735769.jpg","small_url":"https:\/\/salt.tikicdn.com\/cache\/75x75\/media\/catalog\/product\/n\/x\/nx7005den--1-.u2470.d20170214.t135317.735769.jpg"},{"large_url":"https:\/\/salt.tikicdn.com\/cache\/w1200\/media\/catalog\/product\/n\/x\/nx7005den--2-.u2470.d20170214.t135317.774898.jpg","medium_url":"https:\/\/salt.tikicdn.com\/cache\/550x550\/media\/catalog\/product\/n\/x\/nx7005den--2-.u2470.d20170214.t135317.774898.jpg","small_url":"https:\/\/salt.tikicdn.com\/cache\/75x75\/media\/catalog\/product\/n\/x\/nx7005den--2-.u2470.d20170214.t135317.774898.jpg"}],"selected":true,"inventory_status":"available","id":310995,"option1":"Black"}],"specifications":[{"name":"Content","attributes":[{"name":"Th\u01b0\u01a1ng hi\u1ec7u","value":"Genius"},{"name":"Xu\u1ea5t x\u1ee9 th\u01b0\u01a1ng hi\u1ec7u","value":"\u0110\u00e0i Loan"},{"name":"K\u00edch th\u01b0\u1edbc","value":"<p>58 x 100 x 39 mm\u00a0<\/p>"},{"name":"\u0110\u1ed9 ph\u00e2n gi\u1ea3i quang h\u1ecdc","value":"1200 dpi"},{"name":"T\u1ea7n s\u1ed1 qu\u00e9t","value":"T\u1ea7n s\u1ed1 RF: 2,4 GHz"},{"name":"Model","value":"NX-7005"},{"name":"L\u01b0u \u00fd","value":"S\u1ea3n ph\u1ea9m s\u1ebd \u0111\u01b0\u1ee3c khui seal \u0111\u1ec3 d\u00e1n tem BH c\u1ee7a Nh\u00e0 cung c\u1ea5p."},{"name":"Xu\u1ea5t x\u1ee9","value":"Trung Qu\u1ed1c"},{"name":"Tr\u1ecdng l\u01b0\u1ee3ng","value":"80 g"}]},{"name":"Operation","attributes":[{"name":"Ki\u1ec3u giao ti\u1ebfp","value":"USB"}]},{"name":"System","attributes":[{"name":"SKU","value":6705260033853}]}],"product_links":[],"services_and_promotions":[],"promotions":[],"stock_item":{"qty":97833,"min_sale_qty":1,"max_sale_qty":1,"preorder_date":false},"installment_info":null,"video_url":"","youtube":"","is_seller_in_chat_whitelist":false}