{"id":56930154,"sku":"9122852013319","name":"Chu\u1ed9t Kh\u00f4ng D\u00e2y S\u1ea1c Pin HXSJ M402 - H\u00e0ng ch\u00ednh h\u00e3ng","url_key":"chuot-khong-day-sac-pin-hxsj-m402-hang-chinh-hang-p56930154","url_path":"chuot-khong-day-sac-pin-hxsj-m402-hang-chinh-hang-p56930154.html?spid=56930156","type":"configurable","book_cover":null,"short_description":"\n\u00a0\nThi\u1ebft k\u1ebf sang tr\u1ecdng\nChu\u1ed9t Kh\u00f4ng D\u00e2y HXSJ M402 \u0111\u01b0\u1ee3c thi\u1ebft k\u1ebf v\u1edbi c\u00e1c \u0111\u01b0\u1eddng cong u\u1ed1n l\u01b0\u1ee3n, bo tr\u00f2n v\u00e0 \u00f4m s\u00e1t l\u00f2ng b\u00e0n tay, gi\u00fap ng\u01b0\u1eddi s\u1eed d\u1ee5ng gi\u1ea3m b\u1edbt s\u1ef1 \u0111au m\u1ecfi c\u1ee7a c\u1ed5 tay v\u00e0 ng\u00f3n tay. Hai b\u00ean th\u00e2n...","price":146000,"list_price":249000,"price_usd":6.2409999999999997,"badges":[{"code":"tikinow","text":"tikinow"}],"discount":103000,"discount_rate":41,"rating_average":4.5,"review_count":50,"order_count":0,"favourite_count":0,"thumbnail_url":"https:\/\/salt.tikicdn.com\/cache\/280x280\/ts\/product\/03\/35\/3f\/f2a4d8f0d21d7b5a80f00844d4777979.jpg","has_ebook":false,"inventory_status":"available","is_visible":true,"productset_group_name":"Thi\u1ebft B\u1ecb S\u1ed1 - Ph\u1ee5 Ki\u1ec7n S\u1ed1\/Ph\u1ee5 ki\u1ec7n m\u00e1y t\u00ednh v\u00e0 Laptop\/Ph\u1ee5 Ki\u1ec7n Ph\u00edm Chu\u1ed9t V\u0103n Ph\u00f2ng\/Chu\u1ed9t V\u0103n Ph\u00f2ng\/Chu\u1ed9t V\u0103n Ph\u00f2ng Kh\u00f4ng D\u00e2y","is_fresh":false,"seller":null,"is_flower":false,"is_gift_card":false,"inventory":{"product_virtual_type":null,"fulfillment_type":"tiki_delivery"},"url_attendant_input_form":"","master_id":null,"salable_type":"","data_version":10,"day_ago_created":185,"categories":{"id":1815,"name":"Thi\u1ebft B\u1ecb S\u1ed1 - Ph\u1ee5 Ki\u1ec7n S\u1ed1","is_leaf":false},"meta_title":"Chu\u1ed9t Kh\u00f4ng D\u00e2y S\u1ea1c Pin HXSJ M402 - H\u00e0ng ch\u00ednh h\u00e3ng","meta_description":"\n\u00a0\nThi\u1ebft k\u1ebf sang tr\u1ecdng\nChu\u1ed9t Kh\u00f4ng D\u00e2y HXSJ M402 \u0111\u01b0\u1ee3c thi\u1ebft k\u1ebf v\u1edbi c\u00e1c \u0111\u01b0\u1eddng cong u\u1ed1n l\u01b0\u1ee3n, bo tr\u00f2n v\u00e0 \u00f4m s\u00e1t l\u00f2ng b\u00e0n tay, gi\u00fap ng\u01b0\u1eddi s\u1eed d\u1ee5ng gi\u1ea3m b\u1edbt s\u1ef1 \u0111au m\u1ecfi c\u1ee7a c\u1ed5 tay v\u00e0 ng\u00f3n tay. Hai b\u00ean th\u00e2n chu\u1ed9t c\u00f3 c\u00e1c kh\u1ed1i h\u00ecnh tam gi\u00e1c nh\u1ecf \u0111\u01b0\u1ee3c s\u1eafp x\u1ebfp li\u1ec1n...","meta_keywords":null,"liked":false,"rating_summary":[],"description":"<span class='description-separate'><\/span>Mode: M402<br \/>\nCh\u1ea5t li\u1ec7u: ABS cao c\u1ea5p, nh\u1ecf g\u1ecdn, th\u1eddi trang<br \/>\nThi\u1ebft k\u1ebf: Hi\u1ec7n \u0111\u1ea1i<br \/>\n\u0110\u1ed9 ph\u00e2n gi\u1ea3i quang \u0111i\u1ec7n: 800,1200,1600<br \/>\nK\u1ebft n\u1ed1i : Kh\u00f4ng d\u00e2y 2.4GHz<br \/>\nCh\u1ebf \u0111\u1ed9 ho\u1ea1t \u0111\u1ed9ng: Quang \u0111i\u1ec7n t\u1eed<br \/>\n\u0110i\u1ec7n \u00e1p \u0111\u1ecbnh m\u1ee9c \/ d\u00f2ng \u0111i\u1ec7n: 3.7V \/ 8mA<br \/>\nLo\u1ea1i pin: s\u1ea1c l\u1ea1i<br \/>\nDung l\u01b0\u1ee3ng pin: 500mAh<br \/>\nTr\u1ecdng l\u01b0\u01a1ng: 167g<p style=\"text-align: center;\"><iframe src=\"\/\/www.youtube.com\/embed\/Mc80LuWyWXI\" width=\"560\" height=\"314\" allowfullscreen=\"allowfullscreen\"><\/iframe><\/p>\n<p style=\"text-align: center;\">\u00a0<\/p>\n<h2>Thi\u1ebft k\u1ebf sang tr\u1ecdng<\/h2>\n<p><strong>Chu\u1ed9t Kh\u00f4ng D\u00e2y HXSJ M402 <\/strong>\u0111\u01b0\u1ee3c thi\u1ebft k\u1ebf v\u1edbi c\u00e1c \u0111\u01b0\u1eddng cong u\u1ed1n l\u01b0\u1ee3n, bo tr\u00f2n v\u00e0 \u00f4m s\u00e1t l\u00f2ng b\u00e0n tay, gi\u00fap ng\u01b0\u1eddi s\u1eed d\u1ee5ng gi\u1ea3m b\u1edbt s\u1ef1 \u0111au m\u1ecfi c\u1ee7a c\u1ed5 tay v\u00e0 ng\u00f3n tay. Hai b\u00ean th\u00e2n chu\u1ed9t c\u00f3 c\u00e1c kh\u1ed1i h\u00ecnh tam gi\u00e1c nh\u1ecf \u0111\u01b0\u1ee3c s\u1eafp x\u1ebfp li\u1ec1n k\u1ec1 nhau t\u1ea1o \u0111\u1ed9 b\u00e1m gi\u00fap c\u00e1c ng\u00f3n tay kh\u00f4ng b\u1ecb tr\u01a1n tr\u01b0\u1ee3t trong qu\u00e1 tr\u00ecnh s\u1eed d\u1ee5ng. Ngo\u00e0i ra k\u00edch th\u01b0\u1edbc nh\u1ecf g\u1ecdn, s\u1ea3n ph\u1ea9m c\u00f3 th\u1ec3 \u0111\u01b0\u1ee3c b\u1ea1n \u0111em theo b\u00ean m\u00ecnh v\u00e0 s\u1eed d\u1ee5ng khi c\u1ea7n thi\u1ebft.<\/p>\n<p>\u00a0<\/p>\n<p><img id=\"https:\/\/salt.tikicdn.com\/ts\/tmp\/39\/4f\/02\/f6df0c8695cb36f9932ae4c402a529e1.jpg\" style=\"display: block; margin-left: auto; margin-right: auto;\" title=\"\" src=\"https:\/\/salt.tikicdn.com\/ts\/tmp\/39\/4f\/02\/f6df0c8695cb36f9932ae4c402a529e1.jpg\" alt=\"\" width=\"750\" height=\"391\" \/><\/p>\n<p>\u00a0<\/p>\n<h2>C\u00f4ng ngh\u1ec7 chu\u1ed9t quang ti\u00ean ti\u1ebfn<\/h2>\n<p>S\u1ea3n ph\u1ea9m \u0111\u01b0\u1ee3c trang b\u1ecb c\u00f4ng ngh\u1ec7 chu\u1ed9t quang ti\u00ean ti\u1ebfn cho \u0111\u1ed9 ph\u00e2n gi\u1ea3i l\u00ean \u0111\u1ebfn 1600dpi. \u0110\u1ed9 ph\u00e2n gi\u1ea3i cao gi\u00fap , chu\u1ed9t c\u00f3 th\u1ec3 di chuy\u1ec3n nhanh v\u00e0 m\u01b0\u1ee3t m\u00e0 tr\u00ean nhi\u1ec1u b\u1ec1n m\u1eb7t, \u0111\u1ea3m b\u1ea3o hi\u1ec7u qu\u1ea3 cho c\u00f4ng vi\u1ec7c, h\u1ecdc t\u1eadp c\u0169ng nh\u01b0 gi\u1ea3i tr\u00ed.<\/p>\n<p>\u00a0<\/p>\n<p><img id=\"https:\/\/salt.tikicdn.com\/ts\/tmp\/5f\/d0\/f7\/051fadf623feb85822aa874e44ce2ff6.jpg\" style=\"display: block; margin-left: auto; margin-right: auto;\" title=\"\" src=\"https:\/\/salt.tikicdn.com\/ts\/tmp\/5f\/d0\/f7\/051fadf623feb85822aa874e44ce2ff6.jpg\" alt=\"\" width=\"750\" height=\"391\" \/><\/p>\n<p>\u00a0<\/p>\n<h2>Th\u1eddi l\u01b0\u1ee3ng pin l\u1edbn 500mAh<\/h2>\n<p>\u0110\u1eb7c bi\u1ec7t, chu\u1ed9t <strong>HXSJ M402 <\/strong> c\u00f3 th\u1ec3 ho\u1ea1t \u0111\u1ed9ng li\u00ean t\u1ee5c v\u1edbi pin s\u1ea1c su\u1ed1t nhi\u1ec1u ng\u00e0y, gi\u00fap b\u1ea1n ti\u1ebft ki\u1ec7m chi ph\u00ed h\u01a1n v\u00e0 kh\u00f4ng c\u00f2n lo l\u1eafng c\u00f4ng vi\u1ec7c b\u1ecb gi\u00e1n \u0111o\u1ea1n gi\u1eefa ch\u1eebng. Ngo\u00e0i ra chu\u1ed9t c\u00f3 th\u1ec3 s\u1ea1c l\u1ea1i pin \u0111\u1ea3m b\u1ea3o ti\u1ebft ki\u1ec7m, b\u1ea3o v\u1ec1 m\u00f4i tr\u01b0\u1eddng.<\/p>\n<p>\u00a0<\/p>\n<p><img id=\"https:\/\/salt.tikicdn.com\/ts\/tmp\/4c\/36\/3e\/860987e87d07a351d00f66ac49bb5f5b.jpg\" style=\"display: block; margin-left: auto; margin-right: auto;\" title=\"\" src=\"https:\/\/salt.tikicdn.com\/ts\/tmp\/4c\/36\/3e\/860987e87d07a351d00f66ac49bb5f5b.jpg\" alt=\"\" width=\"750\" height=\"391\" \/><\/p>\n<p>\u00a0<\/p>\n<h5>Kh\u00f4ng g\u00e2y ra ti\u1ebfng \u0111\u1ed9ng khi s\u1eed d\u1ee5ng<\/h5>\n<p>Chu\u1ed9t kh\u00f4ng d\u00e2y <strong>HXSJ M402<\/strong> \u0111\u01b0\u1ee3c g\u1eafn m\u00e3 Quiet Mark, ngh\u0129a l\u00e0 kh\u00f4ng g\u00e2y ra ti\u1ebfng \u0111\u1ed9ng trong qu\u00e1 tr\u00ecnh s\u1eed d\u1ee5ng. \u0110i\u1ec1u n\u00e0y \u0111\u1eb7c bi\u1ec7t h\u1eefu \u00edch v\u1edbi nh\u1eefng ng\u01b0\u1eddi l\u00e0m vi\u1ec7c \u0111\u00eam tr\u00e1nh \u1ea3nh h\u01b0\u1edfng t\u1edbi nh\u1eefng ng\u01b0\u1eddi xung quanh, ho\u1eb7c trong m\u00f4i tr\u01b0\u1eddng y\u00eau c\u1ea7u s\u1ef1 y\u00ean l\u1eb7ng.<\/p>\n<p>\u00a0<\/p>\n<p><img id=\"https:\/\/salt.tikicdn.com\/ts\/tmp\/5c\/83\/01\/ccda444719fe7a625ef94177a74a02f8.jpg\" style=\"display: block; margin-left: auto; margin-right: auto;\" title=\"\" src=\"https:\/\/salt.tikicdn.com\/ts\/tmp\/5c\/83\/01\/ccda444719fe7a625ef94177a74a02f8.jpg\" alt=\"\" width=\"750\" height=\"750\" \/><\/p>\n<p>\u00a0<\/p>\n<h2><strong>Chu\u1ed9t Kh\u00f4ng D\u00e2y S\u1ea1c \u0110i\u1ec7n HXSJ M402 <\/strong><\/h2>\n<p>K\u1ebft n\u1ed1i kh\u00f4ng d\u00e2y 2.4GHz, kho\u1ea3ng c\u00e1ch k\u1ebft n\u1ed1i 10m cho b\u1ea1n tho\u1ea3i m\u00e1i l\u01b0\u1edbt chu\u1ed9t m\u00e0 kh\u00f4ng c\u00f2n n\u1ed7i lo v\u01b0\u1edbng v\u00edu d\u00e2y<\/p>\n<p>\u00a0<\/p>\n<p><img id=\"https:\/\/salt.tikicdn.com\/ts\/tmp\/95\/f4\/a6\/47a276bfd6ced296d222628082ecdb49.jpg\" style=\"display: block; margin-left: auto; margin-right: auto;\" title=\"\" src=\"https:\/\/salt.tikicdn.com\/ts\/tmp\/95\/f4\/a6\/47a276bfd6ced296d222628082ecdb49.jpg\" alt=\"\" width=\"750\" height=\"750\" \/><\/p>\n<h2><strong>Chu\u1ed9t Kh\u00f4ng D\u00e2y S\u1ea1c \u0110i\u1ec7n HXSJ M404<\/strong><\/h2>\n<p>C\u00f3 th\u1ec3 s\u1ea1c l\u1ea1i ti\u1ec7n l\u1ee3i, m\u1ed9t l\u1ea7n s\u1ea1c pin c\u00f3 th\u1ec3 s\u1eed d\u1ee5ng \u0111\u01b0\u1ee3c trong th\u1eddi gian d\u00e0i. B\u1ea1n kh\u00f4ng c\u1ea7n ph\u1ea3i pin m\u1edbi v\u00e0 v\u1ee9t b\u1ecf pin c\u0169, g\u00f3p ph\u1ea7n b\u1ea3o v\u1ec7 m\u00f4i tr\u01b0\u1eddng.\u00a0<\/p>\n<p>\u00a0<\/p>\n<p><img id=\"https:\/\/salt.tikicdn.com\/ts\/tmp\/48\/48\/23\/295329783ea43481c6124b7ca9350bbd.jpg\" style=\"display: block; margin-left: auto; margin-right: auto;\" title=\"\" src=\"https:\/\/salt.tikicdn.com\/ts\/tmp\/48\/48\/23\/295329783ea43481c6124b7ca9350bbd.jpg\" alt=\"\" width=\"750\" height=\"750\" \/><\/p>\n<p>\u00a0<\/p>\n<h2><strong>Chu\u1ed9t Kh\u00f4ng D\u00e2y S\u1ea1c \u0110i\u1ec7n HXSJ M80<\/strong><\/h2>\n<p>\u0110\u1ed9 ph\u00e2n gi\u1ea3i cao c\u00f3 th\u1ec3 \u0111i\u1ec1u ch\u1ec9nh: 1600 cho kh\u1ea3 n\u0103ng \u0111\u1ecbnh v\u1ecb chu\u1ed9t cao, nh\u1ea1y v\u00e0 linh ho\u1ea1t khi \u0111i\u1ec1u khi\u1ec3n, h\u1ed7 tr\u1ee3 l\u00e0m vi\u1ec7c, ch\u01a1i game ti\u1ec7n d\u1ee5ng, v\u00e0 l\u01b0\u1edbt \u00eam \u00e1i tr\u00ean m\u1ecdi b\u1ec1 m\u1eb7t<\/p>\n<p><img id=\"https:\/\/salt.tikicdn.com\/ts\/tmp\/b7\/7c\/56\/ae2cf0bc88727958662a2b02bbcd968c.jpg\" style=\"display: block; margin-left: auto; margin-right: auto;\" title=\"\" src=\"https:\/\/salt.tikicdn.com\/ts\/tmp\/b7\/7c\/56\/ae2cf0bc88727958662a2b02bbcd968c.jpg\" alt=\"\" width=\"750\" height=\"750\" \/><\/p><p>Gi\u00e1 s\u1ea3n ph\u1ea9m tr\u00ean Tiki \u0111\u00e3 bao g\u1ed3m thu\u1ebf theo lu\u1eadt hi\u1ec7n h\u00e0nh. Tuy nhi\u00ean tu\u1ef3 v\u00e0o t\u1eebng lo\u1ea1i s\u1ea3n ph\u1ea9m ho\u1eb7c ph\u01b0\u01a1ng th\u1ee9c, \u0111\u1ecba ch\u1ec9 giao h\u00e0ng m\u00e0 c\u00f3 th\u1ec3 ph\u00e1t sinh th\u00eam chi ph\u00ed kh\u00e1c nh\u01b0 ph\u00ed v\u1eadn chuy\u1ec3n, ph\u1ee5 ph\u00ed h\u00e0ng c\u1ed3ng k\u1ec1nh, ...<\/p>","return_policy":null,"warranty_policy":null,"brand":{"id":302375,"name":"HXSJ","slug":"hxsj"},"seller_specifications":[{"name":"Tiki ho\u00e0n ti\u1ec1n 111% n\u1ebfu ph\u00e1t hi\u1ec7n h\u00e0ng gi\u1ea3","value":null,"url":null},{"name":"Cam k\u1ebft h\u00e0ng ch\u00ednh hi\u1ec7u","value":null,"url":null}],"current_seller":{"id":4997,"sku":"3918897237256","store_id":4908,"name":"KIDOS","slug":"kidos","link":"https:\/\/tiki.vn\/cua-hang\/kidos","is_best_store":false,"logo":"https:\/\/vcdn.tikicdn.com\/ts\/seller\/60\/4e\/58\/a18ebc77f6cded5d01cd2a6a80397092.jpg","product_id":"56930156","price":146000,"is_offline_installment_supported":null},"other_sellers":[],"configurable_options":[{"code":"option1","name":"M\u00e0u s\u1eafc","position":0,"values":[{"label":"B\u1ea1c"},{"label":"\u0110en"}]}],"configurable_products":[{"child_id":56930157,"sku":"6373019582121","name":"Chu\u1ed9t Kh\u00f4ng D\u00e2y S\u1ea1c Pin HXSJ M402 - H\u00e0ng ch\u00ednh h\u00e3ng - Tr\u1eafng","price":149000,"thumbnail_url":"https:\/\/salt.tikicdn.com\/cache\/280x280\/ts\/product\/dc\/f1\/35\/ffc596fd7f0be8c3b7e67d8b835dbf6b.jpg","images":[{"large_url":"https:\/\/salt.tikicdn.com\/cache\/w1200\/ts\/product\/dc\/f1\/35\/ffc596fd7f0be8c3b7e67d8b835dbf6b.jpg","medium_url":"https:\/\/salt.tikicdn.com\/cache\/550x550\/ts\/product\/dc\/f1\/35\/ffc596fd7f0be8c3b7e67d8b835dbf6b.jpg","small_url":"https:\/\/salt.tikicdn.com\/cache\/75x75\/ts\/product\/dc\/f1\/35\/ffc596fd7f0be8c3b7e67d8b835dbf6b.jpg"},{"large_url":"https:\/\/salt.tikicdn.com\/cache\/w1200\/ts\/product\/14\/2f\/b9\/8d2db05f8be6b13457b5e52245904705.jpg","medium_url":"https:\/\/salt.tikicdn.com\/cache\/550x550\/ts\/product\/14\/2f\/b9\/8d2db05f8be6b13457b5e52245904705.jpg","small_url":"https:\/\/salt.tikicdn.com\/cache\/75x75\/ts\/product\/14\/2f\/b9\/8d2db05f8be6b13457b5e52245904705.jpg"},{"large_url":"https:\/\/salt.tikicdn.com\/cache\/w1200\/ts\/product\/22\/23\/09\/1823cc113224f8b105d103c5039d47fc.jpg","medium_url":"https:\/\/salt.tikicdn.com\/cache\/550x550\/ts\/product\/22\/23\/09\/1823cc113224f8b105d103c5039d47fc.jpg","small_url":"https:\/\/salt.tikicdn.com\/cache\/75x75\/ts\/product\/22\/23\/09\/1823cc113224f8b105d103c5039d47fc.jpg"},{"large_url":"https:\/\/salt.tikicdn.com\/cache\/w1200\/ts\/product\/0d\/38\/79\/633f9093648b8a8c2cf4f218741c3801.jpg","medium_url":"https:\/\/salt.tikicdn.com\/cache\/550x550\/ts\/product\/0d\/38\/79\/633f9093648b8a8c2cf4f218741c3801.jpg","small_url":"https:\/\/salt.tikicdn.com\/cache\/75x75\/ts\/product\/0d\/38\/79\/633f9093648b8a8c2cf4f218741c3801.jpg"},{"large_url":"https:\/\/salt.tikicdn.com\/cache\/w1200\/ts\/product\/b7\/7c\/56\/eab6b798270eb32964d765881c418553.jpg","medium_url":"https:\/\/salt.tikicdn.com\/cache\/550x550\/ts\/product\/b7\/7c\/56\/eab6b798270eb32964d765881c418553.jpg","small_url":"https:\/\/salt.tikicdn.com\/cache\/75x75\/ts\/product\/b7\/7c\/56\/eab6b798270eb32964d765881c418553.jpg"},{"large_url":"https:\/\/salt.tikicdn.com\/cache\/w1200\/ts\/product\/95\/f4\/a6\/3112b1242e235a46d2da5fe4c04540a3.jpg","medium_url":"https:\/\/salt.tikicdn.com\/cache\/550x550\/ts\/product\/95\/f4\/a6\/3112b1242e235a46d2da5fe4c04540a3.jpg","small_url":"https:\/\/salt.tikicdn.com\/cache\/75x75\/ts\/product\/95\/f4\/a6\/3112b1242e235a46d2da5fe4c04540a3.jpg"},{"large_url":"https:\/\/salt.tikicdn.com\/cache\/w1200\/ts\/product\/48\/48\/23\/4bb4c968c8fdfa805789928e02844ad8.jpg","medium_url":"https:\/\/salt.tikicdn.com\/cache\/550x550\/ts\/product\/48\/48\/23\/4bb4c968c8fdfa805789928e02844ad8.jpg","small_url":"https:\/\/salt.tikicdn.com\/cache\/75x75\/ts\/product\/48\/48\/23\/4bb4c968c8fdfa805789928e02844ad8.jpg"},{"large_url":"https:\/\/salt.tikicdn.com\/cache\/w1200\/ts\/product\/5c\/83\/01\/f1e03a66427620b4ce33c336c17cf7ca.jpg","medium_url":"https:\/\/salt.tikicdn.com\/cache\/550x550\/ts\/product\/5c\/83\/01\/f1e03a66427620b4ce33c336c17cf7ca.jpg","small_url":"https:\/\/salt.tikicdn.com\/cache\/75x75\/ts\/product\/5c\/83\/01\/f1e03a66427620b4ce33c336c17cf7ca.jpg"}],"selected":false,"inventory_status":"available","id":56930158,"option1":"B\u1ea1c"},{"child_id":56930155,"sku":"8205501254149","name":"Chu\u1ed9t Kh\u00f4ng D\u00e2y S\u1ea1c Pin HXSJ M402 - H\u00e0ng ch\u00ednh h\u00e3ng - \u0110en","price":146000,"thumbnail_url":"https:\/\/salt.tikicdn.com\/cache\/280x280\/ts\/product\/03\/35\/3f\/f2a4d8f0d21d7b5a80f00844d4777979.jpg","images":[{"large_url":"https:\/\/salt.tikicdn.com\/cache\/w1200\/ts\/product\/03\/35\/3f\/f2a4d8f0d21d7b5a80f00844d4777979.jpg","medium_url":"https:\/\/salt.tikicdn.com\/cache\/550x550\/ts\/product\/03\/35\/3f\/f2a4d8f0d21d7b5a80f00844d4777979.jpg","small_url":"https:\/\/salt.tikicdn.com\/cache\/75x75\/ts\/product\/03\/35\/3f\/f2a4d8f0d21d7b5a80f00844d4777979.jpg"},{"large_url":"https:\/\/salt.tikicdn.com\/cache\/w1200\/ts\/product\/10\/08\/80\/9acc5af97216cdcbdc10244cfb6a6851.jpg","medium_url":"https:\/\/salt.tikicdn.com\/cache\/550x550\/ts\/product\/10\/08\/80\/9acc5af97216cdcbdc10244cfb6a6851.jpg","small_url":"https:\/\/salt.tikicdn.com\/cache\/75x75\/ts\/product\/10\/08\/80\/9acc5af97216cdcbdc10244cfb6a6851.jpg"},{"large_url":"https:\/\/salt.tikicdn.com\/cache\/w1200\/ts\/product\/82\/96\/75\/732b082e6e50c7c436592dc3b425f424.jpg","medium_url":"https:\/\/salt.tikicdn.com\/cache\/550x550\/ts\/product\/82\/96\/75\/732b082e6e50c7c436592dc3b425f424.jpg","small_url":"https:\/\/salt.tikicdn.com\/cache\/75x75\/ts\/product\/82\/96\/75\/732b082e6e50c7c436592dc3b425f424.jpg"},{"large_url":"https:\/\/salt.tikicdn.com\/cache\/w1200\/ts\/product\/ae\/2f\/16\/b922956d7904e20689cb05781b93d9fe.jpg","medium_url":"https:\/\/salt.tikicdn.com\/cache\/550x550\/ts\/product\/ae\/2f\/16\/b922956d7904e20689cb05781b93d9fe.jpg","small_url":"https:\/\/salt.tikicdn.com\/cache\/75x75\/ts\/product\/ae\/2f\/16\/b922956d7904e20689cb05781b93d9fe.jpg"},{"large_url":"https:\/\/salt.tikicdn.com\/cache\/w1200\/ts\/product\/a5\/6b\/97\/2e3abdde59387f06effe16192408bb5a.jpg","medium_url":"https:\/\/salt.tikicdn.com\/cache\/550x550\/ts\/product\/a5\/6b\/97\/2e3abdde59387f06effe16192408bb5a.jpg","small_url":"https:\/\/salt.tikicdn.com\/cache\/75x75\/ts\/product\/a5\/6b\/97\/2e3abdde59387f06effe16192408bb5a.jpg"},{"large_url":"https:\/\/salt.tikicdn.com\/cache\/w1200\/ts\/product\/8c\/a6\/4a\/58b063d23ae093a478a6fa49dd245572.jpg","medium_url":"https:\/\/salt.tikicdn.com\/cache\/550x550\/ts\/product\/8c\/a6\/4a\/58b063d23ae093a478a6fa49dd245572.jpg","small_url":"https:\/\/salt.tikicdn.com\/cache\/75x75\/ts\/product\/8c\/a6\/4a\/58b063d23ae093a478a6fa49dd245572.jpg"},{"large_url":"https:\/\/salt.tikicdn.com\/cache\/w1200\/ts\/product\/5c\/83\/01\/b752e2fdeaa1986979e8933acd7b4c6e.jpg","medium_url":"https:\/\/salt.tikicdn.com\/cache\/550x550\/ts\/product\/5c\/83\/01\/b752e2fdeaa1986979e8933acd7b4c6e.jpg","small_url":"https:\/\/salt.tikicdn.com\/cache\/75x75\/ts\/product\/5c\/83\/01\/b752e2fdeaa1986979e8933acd7b4c6e.jpg"},{"large_url":"https:\/\/salt.tikicdn.com\/cache\/w1200\/ts\/product\/95\/f4\/a6\/7e8578e1e6a6a7dd659f39ac1cb6bd36.jpg","medium_url":"https:\/\/salt.tikicdn.com\/cache\/550x550\/ts\/product\/95\/f4\/a6\/7e8578e1e6a6a7dd659f39ac1cb6bd36.jpg","small_url":"https:\/\/salt.tikicdn.com\/cache\/75x75\/ts\/product\/95\/f4\/a6\/7e8578e1e6a6a7dd659f39ac1cb6bd36.jpg"},{"large_url":"https:\/\/salt.tikicdn.com\/cache\/w1200\/ts\/product\/48\/48\/23\/d74b0827f5f53ec424dbda4bbded0661.jpg","medium_url":"https:\/\/salt.tikicdn.com\/cache\/550x550\/ts\/product\/48\/48\/23\/d74b0827f5f53ec424dbda4bbded0661.jpg","small_url":"https:\/\/salt.tikicdn.com\/cache\/75x75\/ts\/product\/48\/48\/23\/d74b0827f5f53ec424dbda4bbded0661.jpg"},{"large_url":"https:\/\/salt.tikicdn.com\/cache\/w1200\/ts\/product\/b7\/7c\/56\/b6808a201f1991509436be974928ec32.jpg","medium_url":"https:\/\/salt.tikicdn.com\/cache\/550x550\/ts\/product\/b7\/7c\/56\/b6808a201f1991509436be974928ec32.jpg","small_url":"https:\/\/salt.tikicdn.com\/cache\/75x75\/ts\/product\/b7\/7c\/56\/b6808a201f1991509436be974928ec32.jpg"}],"selected":true,"inventory_status":"available","id":56930156,"option1":"\u0110en"}],"specifications":[{"name":"Content","attributes":[{"name":"Th\u01b0\u01a1ng hi\u1ec7u","value":"HXSJ"},{"name":"Xu\u1ea5t x\u1ee9 th\u01b0\u01a1ng hi\u1ec7u","value":"Trung Qu\u1ed1c"},{"name":"\u0110\u1ed9 ph\u00e2n gi\u1ea3i quang h\u1ecdc","value":"800,1200,1600"},{"name":"Model","value":"HXSJ M402"},{"name":"Ch\u1ea5t li\u1ec7u","value":"ABS"},{"name":"Xu\u1ea5t x\u1ee9","value":"Trung Qu\u1ed1c"},{"name":"Tr\u1ecdng l\u01b0\u1ee3ng","value":"67g"},{"name":"H\u1ec7 \u0111i\u1ec1u h\u00e0nh","value":"Windows 98 \/ Me \/ 2000 \/ XP \/ Vista \/ Win 7 \/ Win8 \/ 10\/Vista Mac OS or latest."}]},{"name":"System","attributes":[{"name":"SKU","value":9122852013319}]}],"product_links":[],"services_and_promotions":[],"promotions":[],"stock_item":{"qty":192694,"min_sale_qty":1,"max_sale_qty":20,"preorder_date":false},"installment_info":null,"video_url":"","youtube":"","is_seller_in_chat_whitelist":true}